<?xml version="1.0" encoding="UTF-8"?>
<flow id="62b595b3-e393-4c1a-979d-255d4487fa8c">
  <descriptionCdata><![CDATA[62b595b3-e393-4c1a-979d-255d4487fa8c.09d3017c-6797-4311-945b-53fe20c440bf.prompt=message1
62b595b3-e393-4c1a-979d-255d4487fa8c.8e263845-87f0-4a65-93f8-e005f4a6b80a.prompt=message2
62b595b3-e393-4c1a-979d-255d4487fa8c.b462e9b9-42d2-4f8f-83fb-bd659d7a55e1.description=<pre>This is an operation that does nothing. It can be used for filtering flow variables by feeding them in as inputs and filtering them on the results tab.\n\nResponses\:\n    success\n    failure\n</pre>
62b595b3-e393-4c1a-979d-255d4487fa8c.e6014808-0185-4405-bff5-e8bf51b9dc36.prompt=message3
]]></descriptionCdata>
  <annotation></annotation>
  <name>f1</name>
  <categories/>
  <inputs>
    <userInputBinding id="09d3017c-6797-4311-945b-53fe20c440bf">
      <annotation></annotation>
      <assignFromContext>false</assignFromContext>
      <assignToContext>false</assignToContext>
      <inputType>STRING</inputType>
      <isList>false</isList>
      <required>false</required>
      <isPersisted>true</isPersisted>
      <inputSymbol>inp1</inputSymbol>
      <listDelimiter>,</listDelimiter>
      <record>false</record>
      <prompt>62b595b3-e393-4c1a-979d-255d4487fa8c.09d3017c-6797-4311-945b-53fe20c440bf.prompt</prompt>
      <isMultiSelect>false</isMultiSelect>
      <link>
        <refId>40e4562a-7197-45ee-9f36-e5d03f255b10</refId>
        <refName>C</refName>
      </link>
      <sourceDelimiter>|</sourceDelimiter>
    </userInputBinding>
    <userInputBinding id="8e263845-87f0-4a65-93f8-e005f4a6b80a">
      <annotation></annotation>
      <assignFromContext>false</assignFromContext>
      <assignToContext>false</assignToContext>
      <inputType>STRING</inputType>
      <isList>false</isList>
      <required>false</required>
      <isPersisted>true</isPersisted>
      <inputSymbol>inp2</inputSymbol>
      <listDelimiter>,</listDelimiter>
      <record>false</record>
      <prompt>62b595b3-e393-4c1a-979d-255d4487fa8c.8e263845-87f0-4a65-93f8-e005f4a6b80a.prompt</prompt>
      <isMultiSelect>false</isMultiSelect>
      <link>
        <refId>58d0d759-0c59-4310-9989-081a7a273863</refId>
        <refName>D</refName>
      </link>
      <sourceDelimiter>|</sourceDelimiter>
    </userInputBinding>
    <userInputBinding id="e6014808-0185-4405-bff5-e8bf51b9dc36">
      <annotation></annotation>
      <assignFromContext>false</assignFromContext>
      <assignToContext>false</assignToContext>
      <inputType>STRING</inputType>
      <isList>false</isList>
      <required>false</required>
      <isPersisted>true</isPersisted>
      <inputSymbol>inp3</inputSymbol>
      <listDelimiter>,</listDelimiter>
      <record>false</record>
      <prompt>62b595b3-e393-4c1a-979d-255d4487fa8c.e6014808-0185-4405-bff5-e8bf51b9dc36.prompt</prompt>
      <isMultiSelect>false</isMultiSelect>
      <dynPickListKey>inp1</dynPickListKey>
      <sourceDelimiter>|</sourceDelimiter>
    </userInputBinding>
    <userInputBinding id="9d47abcb-4c2c-4d79-986f-9a9df0bdbebf">
      <annotation></annotation>
      <assignFromContext>false</assignFromContext>
      <assignToContext>false</assignToContext>
      <inputType>STRING</inputType>
      <isList>false</isList>
      <required>false</required>
      <isPersisted>true</isPersisted>
      <inputSymbol>inp4</inputSymbol>
      <listDelimiter>,</listDelimiter>
      <record>false</record>
      <prompt></prompt>
      <isMultiSelect>false</isMultiSelect>
      <dynPickListKey>inp1</dynPickListKey>
      <sourceDelimiter></sourceDelimiter>
    </userInputBinding>
    <userInputBinding id="3c4fe48f-6b87-4597-815d-41592bac18ed">
      <annotation></annotation>
      <assignFromContext>false</assignFromContext>
      <assignToContext>false</assignToContext>
      <inputType>STRING</inputType>
      <isList>false</isList>
      <required>false</required>
      <isPersisted>true</isPersisted>
      <inputSymbol>inp5</inputSymbol>
      <listDelimiter>,</listDelimiter>
      <record>false</record>
      <validationFormat>
        <refId>2a5d0e55-5a3c-4688-988e-ab7d1e939d66</refId>
        <refName>B</refName>
      </validationFormat>
      <prompt></prompt>
      <isMultiSelect>false</isMultiSelect>
      <sourceDelimiter>|</sourceDelimiter>
    </userInputBinding>
  </inputs>
  <possibleResponses>
    <opResponse id="06d12c0b-d9ee-4fe4-8c24-3975776e2b35">
      <annotation></annotation>
      <name>success</name>
      <isDefault>true</isDefault>
      <onFailure>false</onFailure>
      <type>RESOLVED</type>
      <matchRules/>
    </opResponse>
  </possibleResponses>
  <availableResultExpressions/>
  <resultExpression id="71e576f7-3ef5-49a5-ab6b-49b5e0f33f75">
    <annotation></annotation>
    <name>FailureMessage</name>
    <fieldName>FailureMessage</fieldName>
    <sourceType>RAWRESULT</sourceType>
    <filters/>
  </resultExpression>
  <iconSpec id="ed2d421d-1495-4dba-bbf4-da5540f1e2f1">
    <baseIcon>flow.png</baseIcon>
    <basePath>System</basePath>
    <readOnly>false</readOnly>
    <layers/>
  </iconSpec>
  <callouts/>
  <checkPointFlow>true</checkPointFlow>
  <compatibleRuntimeContext>false</compatibleRuntimeContext>
  <historyCheckPointFlow>true</historyCheckPointFlow>
  <steps>
    <step id="b462e9b9-42d2-4f8f-83fb-bd659d7a55e1">
      <annotation>62b595b3-e393-4c1a-979d-255d4487fa8c.b462e9b9-42d2-4f8f-83fb-bd659d7a55e1.description</annotation>
      <name>Do Nothing With Two Responses</name>
      <bounds>
        <x>283.0</x>
        <y>313.0</y>
      </bounds>
      <layer>-1</layer>
      <hideInbound>false</hideInbound>
      <addResultToRunContext>false</addResultToRunContext>
      <isCriticalStep>false</isCriticalStep>
      <isNonBlocking>false</isNonBlocking>
      <isParallelStep>false</isParallelStep>
      <isSingleResponse>false</isSingleResponse>
      <recordInHistory>false</recordInHistory>
      <recordRawOutput>true</recordRawOutput>
      <recordPrimaryOutput>true</recordPrimaryOutput>
      <checkPointStep>true</checkPointStep>
      <historyCheckPointStep>true</historyCheckPointStep>
      <scriptResultStep>false</scriptResultStep>
      <userPrompt></userPrompt>
      <bindings/>
      <transitions>
        <transition id="fd67ba87-fafd-4312-bca5-bab4a91edb52">
          <annotation></annotation>
          <name>success</name>
          <command>NEXT</command>
          <linkMode>false</linkMode>
          <responseSymbol>success</responseSymbol>
          <shouldHandoff>false</shouldHandoff>
          <transitionValue>0.0</transitionValue>
          <destination>
            <refId>2981a293-a828-450b-8619-1a0d742db1de</refId>
          </destination>
          <source>
            <refId>b462e9b9-42d2-4f8f-83fb-bd659d7a55e1</refId>
          </source>
          <positions>
            <point>
              <x>333.0</x>
              <y>347.0</y>
            </point>
            <point>
              <x>621.0</x>
              <y>331.0</y>
            </point>
          </positions>
          <labelPosition>
            <x>333.0</x>
            <y>0.0</y>
          </labelPosition>
        </transition>
        <transition id="78617400-93fd-4379-bb95-2aea9cf1eeae">
          <annotation></annotation>
          <name>failure</name>
          <command>NEXT</command>
          <linkMode>false</linkMode>
          <responseSymbol>failure</responseSymbol>
          <shouldHandoff>false</shouldHandoff>
          <transitionValue>0.0</transitionValue>
          <destination>
            <refId>2981a293-a828-450b-8619-1a0d742db1de</refId>
          </destination>
          <source>
            <refId>b462e9b9-42d2-4f8f-83fb-bd659d7a55e1</refId>
          </source>
          <positions>
            <point>
              <x>333.0</x>
              <y>347.0</y>
            </point>
            <point>
              <x>394.29437168288786</x>
              <y>368.6333076527839</y>
            </point>
            <point>
              <x>562.4791292982383</x>
              <y>359.2897100074867</y>
            </point>
            <point>
              <x>621.0</x>
              <y>331.0</y>
            </point>
          </positions>
          <labelPosition>
            <x>333.0</x>
            <y>0.0</y>
          </labelPosition>
        </transition>
      </transitions>
      <properties/>
      <opRef>
        <refId>e46b91b4-6637-4b3d-883a-e86436d9eb3a</refId>
      </opRef>
      <assignments/>
      <throttleSize>0</throttleSize>
    </step>
    <returnStep id="2981a293-a828-450b-8619-1a0d742db1de">
      <annotation></annotation>
      <name>Resolved : success</name>
      <bounds>
        <x>571.0</x>
        <y>297.0</y>
      </bounds>
      <layer>-1</layer>
      <hideInbound>false</hideInbound>
      <addResultToRunContext>false</addResultToRunContext>
      <isCriticalStep>false</isCriticalStep>
      <isNonBlocking>false</isNonBlocking>
      <isParallelStep>false</isParallelStep>
      <isSingleResponse>false</isSingleResponse>
      <recordInHistory>false</recordInHistory>
      <recordRawOutput>true</recordRawOutput>
      <recordPrimaryOutput>true</recordPrimaryOutput>
      <checkPointStep>true</checkPointStep>
      <historyCheckPointStep>true</historyCheckPointStep>
      <scriptResultStep>false</scriptResultStep>
      <userPrompt></userPrompt>
      <bindings/>
      <transitions>
        <transition id="619b168d-dc58-47c0-a767-a2df7c653484">
          <annotation></annotation>
          <name>return</name>
          <command>NEXT</command>
          <linkMode>false</linkMode>
          <responseSymbol>success</responseSymbol>
          <shouldHandoff>false</shouldHandoff>
          <transitionValue>0.0</transitionValue>
          <destination>
            <refId>2981a293-a828-450b-8619-1a0d742db1de</refId>
          </destination>
          <source>
            <refId>2981a293-a828-450b-8619-1a0d742db1de</refId>
          </source>
          <positions/>
        </transition>
      </transitions>
      <properties/>
      <returnStepType>RESOLVED</returnStepType>
      <assignments/>
    </returnStep>
  </steps>
  <startSteps>b462e9b9-42d2-4f8f-83fb-bd659d7a55e1</startSteps>
</flow>